MANIFEST.in
README.rst
setup.py
ckanext/__init__.py
ckanext/pdfview/__init__.py
ckanext/pdfview/plugin.py
ckanext/pdfview/tests/__init__.py
ckanext/pdfview/tests/test_view.py
ckanext/pdfview/theme/templates/pdf_form.html
ckanext/pdfview/theme/templates/pdf_view.html
ckanext_pdfview.egg-info/PKG-INFO
ckanext_pdfview.egg-info/SOURCES.txt
ckanext_pdfview.egg-info/dependency_links.txt
ckanext_pdfview.egg-info/entry_points.txt
ckanext_pdfview.egg-info/namespace_packages.txt
ckanext_pdfview.egg-info/top_level.txt