Metadata-Version: 1.1
Name: ckanext-pdfview
Version: 0.0.6
Summary: View plugin for rendering PDFs on the browser
Home-page: https://github.com/ckan/ckanext-pdfview
Author: Open Knowledge
Author-email: info@ckan.org
License: AGPL
Keywords: CKAN PDF
Platform: UNKNOWN
Classifier: Development Status :: 4 - Beta
Classifier: License :: OSI Approved :: GNU Affero General Public License v3 or later (AGPLv3+)
Classifier: Programming Language :: Python :: 2.7
